extarc/__init__.py
extarc/logger.py
extarc/obj.py
extarc/sr.py
extarc/table.py
extarc-0.0.1.dist-info/LICENSE
extarc-0.0.1.dist-info/METADATA
extarc-0.0.1.dist-info/WHEEL
extarc-0.0.1.dist-info/top_level.txt
extarc-0.0.1.dist-info/RECORD
