Metadata-Version: 2.1
Name: extarc
Version: 0.0.1
Summary: A collection of functions for extending ESRI's arcpy module. Mostly utility or helper functions.
Home-page: https://github.com/dorkwood/extarc
Author: Josh P. Sawyer
Author-email: josh.p.sawyer@gmail.com
License: MIT
Platform: UNKNOWN
Classifier: Intended Audience :: Science/Research
Classifier: Programming Language :: Python :: 2.7
Classifier: Programming Language :: Python :: 3
Classifier: Programming Language :: Python :: 3.6
Classifier: License :: OSI Approved :: MIT License
Requires-Python: >=2.7
